{
  "update_time": "2026-02-10 08:49:06",
  "count": 20,
  "data": [
    {
      "school_id": 140,
      "name": "清华大学",
      "province": "北京",
      "city": "北京市",
      "county": "海淀区",
      "type": "综合类",
      "level": "本科",
      "belong": "教育部",
      "rank": "1",
      "dual_class": "双一流",
      "f985": 1,
      "f211": 1,
      "is_dual_class": "38000",
      "nature": "公办",
      "view_total": "3061w",
      "content": "清华大学的前身清华学堂始建于1911年，1912年更名为清华学校。1928年更名为国立清华大学。1937年抗日战争全面爆发后南迁长沙，与北京大学、南开大学组建国立长沙临时大学，1938年迁至昆明改名为国立西南联合大学。1946年迁回清华园，设有文、法、理、工、农等5个学院、26个系。1952年全国高等学校院系调整后，清华大学成为一所多科性工业大学，重点为国家培养工程技术人",
      "email": "zsb@tsinghua.edu.cn",
      "school_email": "",
      "site": "https://www.join-tsinghua.edu.cn",
      "school_site": "https://www.tsinghua.edu.cn",
      "address": "北京市海淀区清华大学",
      "phone": "010-62770334,010-62782051",
      "school_phone": "",
      "postcode": "100084",
      "logo": null,
      "create_date": "1911",
      "old_name": "",
      "area": 7230,
      "num_doctor": "64",
      "num_master": "68",
      "num_subject": "21",
      "num_academician": "89",
      "num_library": "568.35万",
      "recommend_master_rate": "70.00",
      "motto": "自强不息，厚德载物",
      "ruanke_rank": "1",
      "xyh_rank": "2",
      "wsl_rank": "0",
      "qs_rank": "1",
      "us_rank": "11",
      "label_list": [
        "985",
        "211",
        "双一流",
        "强基",
        "101计划",
        "C9",
        "机械五虎",
        "电气四虎",
        "建筑老八校"
      ],
      "recommend_master_level": "5",
      "is_top": 2,
      "attr_list": [
        "综合类",
        "公办",
        "教育部直属"
      ],
      "hightitle": "清华大学"
    },
    {
      "school_id": 31,
      "name": "北京大学",
      "province": "北京",
      "city": "北京市",
      "county": "海淀区",
      "type": "综合类",
      "level": "本科",
      "belong": "教育部",
      "rank": "2",
      "dual_class": "双一流",
      "f985": 1,
      "f211": 1,
      "is_dual_class": "38000",
      "nature": "公办",
      "view_total": "2769w",
      "content": "北京大学创办于1898年，是戊戌变法的产物，也是中华民族救亡图存、兴学图强的结果，初名京师大学堂，是中国近现代第一所国立综合性大学，辛亥革命后，于1912年改为现名。在悠久的文明历程中，古代中国曾创立太学、国子学、国子监等国家最高学府，在中国和世界教育史上具有重要影响。北京大学“上承太学正统，下立大学祖庭”，既是中华文脉和教育传统的传承者，也",
      "email": "bdzsb@pku.edu.cn",
      "school_email": "its@pku.edu.cn",
      "site": "https://www.gotopku.cn/",
      "school_site": "https://www.pku.edu.cn/",
      "address": "燕园校区（校本部）：北京市海淀区颐和园路5号,医学部校区：北京市海淀区学院路38号,昌平校区：北京市昌平区十三陵镇西山口村,大兴校区：北京市大兴工业开发区金苑路24号,无锡校区：江苏省无锡市滨湖区雪浪街道大学城状元道5号,深圳研究生院：深圳市南山区西丽镇丽水路深圳大学城北大校区,昌平新校区：北京市昌平区十三陵镇西山口村",
      "phone": "010-62751407",
      "school_phone": "",
      "postcode": "100871",
      "logo": null,
      "create_date": "1898",
      "old_name": "",
      "area": 4127,
      "num_doctor": "53",
      "num_master": "50",
      "num_subject": "18",
      "num_academician": "162",
      "num_library": "851.20万",
      "recommend_master_rate": "50.57",
      "motto": "",
      "ruanke_rank": "2",
      "xyh_rank": "1",
      "wsl_rank": "0",
      "qs_rank": "2",
      "us_rank": "25",
      "label_list": [
        "985",
        "211",
        "双一流",
        "强基",
        "101计划",
        "C9",
        "五院四系",
        "医药双雄"
      ],
      "recommend_master_level": "5",
      "is_top": 2,
      "attr_list": [
        "综合类",
        "公办",
        "教育部直属"
      ],
      "hightitle": "北京大学"
    },
    {
      "school_id": 114,
      "name": "浙江大学",
      "province": "浙江",
      "city": "杭州市",
      "county": "西湖区",
      "type": "综合类",
      "level": "本科",
      "belong": "教育部",
      "rank": "3",
      "dual_class": "双一流",
      "f985": 1,
      "f211": 1,
      "is_dual_class": "38000",
      "nature": "公办",
      "view_total": "2322.7w",
      "content": "浙江大学是一所历史悠久、声誉卓著的高等学府，坐落于中国历史文化名城、风景旅游胜地杭州。浙江大学的前身求是书院创立于1897年，为中国人自己最早创办的新式高等学校之一。1928年，定名国立浙江大学。抗战期间，浙大举校西迁，在贵州遵义、湄潭等地办学七年，1946年秋回迁杭州。1952年全国高等学校院系调整时，浙江大学部分系科转入兄弟高校和中国科学院，留在杭",
      "email": "zsc@zju.edu.cn",
      "school_email": "",
      "site": "https://zdzsc.zju.edu.cn",
      "school_site": "https://www.zju.edu.cn/",
      "address": "紫金港校区：浙江省杭州市西湖区余杭塘路866号,宁波校区：浙江省宁波市钱湖南路1号,玉泉校区：浙江省杭州市西湖区浙大路38号,西溪校区：浙江省杭州市西湖区天目山路148号,华家池校区：浙江省杭州市江干区凯旋路268号,之江校区：浙江省杭州市西湖区之江路51号,舟山校区：浙江省舟山市定海区浙大路1号,海宁校区：浙江省海宁市海州东路718号",
      "phone": "0571-87951006",
      "school_phone": "",
      "postcode": "310058",
      "logo": null,
      "create_date": "1897",
      "old_name": "",
      "area": 11146,
      "num_doctor": "62",
      "num_master": "62",
      "num_subject": "13",
      "num_academician": "26",
      "num_library": "819.20万",
      "recommend_master_rate": "38.94",
      "motto": "求是创新",
      "ruanke_rank": "3",
      "xyh_rank": "5",
      "wsl_rank": "0",
      "qs_rank": "5",
      "us_rank": "45",
      "label_list": [
        "985",
        "211",
        "双一流",
        "强基",
        "101计划",
        "C9",
        "华东五虎",
        "电气四虎",
        "建筑新八校"
      ],
      "recommend_master_level": "4.5",
      "is_top": 2,
      "attr_list": [
        "综合类",
        "公办",
        "教育部直属"
      ],
      "hightitle": "浙江大学"
    },
    {
      "school_id": 125,
      "name": "上海交通大学",
      "province": "上海",
      "city": "上海市",
      "county": "闵行区",
      "type": "综合类",
      "level": "本科",
      "belong": "教育部",
      "rank": "4",
      "dual_class": "双一流",
      "f985": 1,
      "f211": 1,
      "is_dual_class": "38000",
      "nature": "公办",
      "view_total": "2824.9w",
      "content": "上海交通大学是我国历史最悠久、享誉海内外的高等学府之一，是教育部直属并与上海市共建的全国重点大学。经过120多年的不懈努力，上海交通大学已经建设成为一所“综合性、创新型、国际化”的国内一流、国际知名大学。十九世纪末，甲午战败，民族危难。中国近代著名实业家、教育家盛宣怀秉持“自强首在储才，储才必先兴学”的信念，于1896年在上海创办了交通大学",
      "email": "zsb@sjtu.edu.cn",
      "school_email": "",
      "site": "https://admissions.sjtu.edu.cn",
      "school_site": "https://www.sjtu.edu.cn/",
      "address": "闵行校区：上海市闵行区东川路800号,徐汇校区：上海市徐汇区华山路1954号,黄浦校区：上海市重庆南路227号,长宁校区：上海市长宁区法华镇路535号,浦东校区：上海市浦东新区红枫路699号",
      "phone": "021-34200000,021-34207255",
      "school_phone": "",
      "postcode": "200240",
      "logo": null,
      "create_date": "1896",
      "old_name": "",
      "area": 4500,
      "num_doctor": "52",
      "num_master": "57",
      "num_subject": "0",
      "num_academician": "33",
      "num_library": "385.20万",
      "recommend_master_rate": "45.01",
      "motto": "饮水思源，爱国荣校",
      "ruanke_rank": "4",
      "xyh_rank": "5",
      "wsl_rank": "0",
      "qs_rank": "6",
      "us_rank": "46",
      "label_list": [
        "985",
        "211",
        "双一流",
        "强基",
        "101计划",
        "C9",
        "华东五虎",
        "机械五虎",
        "建筑新八校"
      ],
      "recommend_master_level": "5",
      "is_top": 2,
      "attr_list": [
        "综合类",
        "公办",
        "教育部直属"
      ],
      "hightitle": "上海交通大学"
    },
    {
      "school_id": 132,
      "name": "复旦大学",
      "province": "上海",
      "city": "上海市",
      "county": "杨浦区",
      "type": "综合类",
      "level": "本科",
      "belong": "教育部",
      "rank": "5",
      "dual_class": "双一流",
      "f985": 1,
      "f211": 1,
      "is_dual_class": "38000",
      "nature": "公办",
      "view_total": "2488.3w",
      "content": "复旦大学校名取自《尚书大传》之“日月光华，旦复旦兮”，始创于1905年，原名复旦公学，1917年定名为复旦大学，是中国人自主创办的第一所高等院校。上海医科大学前身是1927年创办的国立第四中山大学医学院。2000年，复旦大学与上海医科大学合并。目前，学校拥有哲学、经济学、法学、教育学、文学、历史学、理学、工学、医学、管理学、艺术学、交叉学科等12个学科门",
      "email": "admission@fudan.edu.cn",
      "school_email": "",
      "site": "https://ao.fudan.edu.cn/",
      "school_site": "https://www.fudan.edu.cn",
      "address": "邯郸校区：上海市杨浦区邯郸路220号,枫林校区：上海市徐汇区东安路130号,张江校区：上海市浦东新区张江高科技园区张衡路825号,江湾校区：上海市杨浦区淞沪路2005号",
      "phone": "021-55666668",
      "school_phone": "",
      "postcode": "200433",
      "logo": null,
      "create_date": "1905",
      "old_name": "",
      "area": 3616,
      "num_doctor": "44",
      "num_master": "47",
      "num_subject": "0",
      "num_academician": "59",
      "num_library": "623.04万",
      "recommend_master_rate": "41.95",
      "motto": "博学而笃志，切问而近思",
      "ruanke_rank": "5",
      "xyh_rank": "4",
      "wsl_rank": "0",
      "qs_rank": "3",
      "us_rank": "70",
      "label_list": [
        "985",
        "211",
        "双一流",
        "强基",
        "101计划",
        "C9",
        "华东五虎",
        "医药双雄"
      ],
      "recommend_master_level": "5",
      "is_top": 2,
      "attr_list": [
        "综合类",
        "公办",
        "教育部直属"
      ],
      "hightitle": "复旦大学"
    },
    {
      "school_id": 111,
      "name": "南京大学",
      "province": "江苏",
      "city": "南京市",
      "county": "鼓楼区",
      "type": "综合类",
      "level": "本科",
      "belong": "教育部",
      "rank": "6",
      "dual_class": "双一流",
      "f985": 1,
      "f211": 1,
      "is_dual_class": "38000",
      "nature": "公办",
      "view_total": "3355w",
      "content": "南京大学是一所历史悠久、声誉卓著的高等学府。其前身是创建于1902年的三江师范学堂，此后历经两江师范学堂、南京高等师范学校、国立东南大学、国立第四中山大学、国立中央大学、国立南京大学等历史时期，于1950年更名为南京大学。1952年，在全国高校院系调整中，南京大学调整出工学、农学、师范等部分院系后与创办于1888年的金陵大学文、理学院等合并，仍名南京大",
      "email": "bkzs@nju.edu.cn",
      "school_email": "",
      "site": "https://bkzs.nju.edu.cn",
      "school_site": "https://www.nju.edu.cn/",
      "address": "仙林校区：江苏省南京市栖霞区仙林大道163号,鼓楼校区：江苏省南京市鼓楼区汉口路22号,浦口校区：江苏省南京市浦口区沿江镇学府路8号,苏州校区：江苏省苏州市虎丘区太湖大道",
      "phone": "400-1859680",
      "school_phone": "",
      "postcode": "210093",
      "logo": null,
      "create_date": "1902",
      "old_name": "",
      "area": 0,
      "num_doctor": "43",
      "num_master": "4",
      "num_subject": "0",
      "num_academician": "34",
      "num_library": "682.86万",
      "recommend_master_rate": "48.74",
      "motto": "诚朴雄伟，励学敦行",
      "ruanke_rank": "6",
      "xyh_rank": "6",
      "wsl_rank": "0",
      "qs_rank": "7",
      "us_rank": "86",
      "label_list": [
        "985",
        "211",
        "双一流",
        "强基",
        "101计划",
        "C9",
        "华东五虎",
        "建筑新八校"
      ],
      "recommend_master_level": "5",
      "is_top": 2,
      "attr_list": [
        "综合类",
        "公办",
        "教育部直属"
      ],
      "hightitle": "南京大学"
    },
    {
      "school_id": 66,
      "name": "中国科学技术大学",
      "province": "安徽",
      "city": "合肥市",
      "county": "包河区",
      "type": "理工类",
      "level": "本科",
      "belong": "中国科学院",
      "rank": "7",
      "dual_class": "双一流",
      "f985": 1,
      "f211": 1,
      "is_dual_class": "38000",
      "nature": "公办",
      "view_total": "1357w",
      "content": "中国科学技术大学是中国科学院所属的一所以前沿科学和高新技术为主，兼有医学、特色管理和人文学科的理工科大学。学校现有32个学院，含8个科教融合学院；设有苏州高等研究院、上海研究院、北京研究院、先进技术研究院、国际金融研究院、附属第一医院（安徽省立医院）。学校于1958年9月在北京创建，郭沫若任首任校长。这是我党为“两弹一星”事业而创办的红色大学",
      "email": "zsb@ustc.edu.cn",
      "school_email": "",
      "site": "https://zsb.ustc.edu.cn",
      "school_site": "https://www.ustc.edu.cn/",
      "address": "东校区：安徽省合肥市包河区金寨路96号,西校区：安徽省合肥市蜀山区黄山路443号,南校区：安徽省合肥市包河区徽州大道1129号,中校区：安徽省合肥市蜀山区黄山路373号,北校区：安徽省合肥市蜀山区金寨路96号",
      "phone": "0551-63602553,0551-63600096",
      "school_phone": "",
      "postcode": "230026",
      "logo": null,
      "create_date": "1958",
      "old_name": "",
      "area": 2475,
      "num_doctor": "34",
      "num_master": "6",
      "num_subject": "8",
      "num_academician": "28",
      "num_library": "67.00万",
      "recommend_master_rate": "62.20",
      "motto": "",
      "ruanke_rank": "7",
      "xyh_rank": "8",
      "wsl_rank": "0",
      "qs_rank": "4",
      "us_rank": "71",
      "label_list": [
        "985",
        "211",
        "双一流",
        "强基",
        "101计划",
        "C9",
        "华东五虎"
      ],
      "recommend_master_level": "5",
      "is_top": 2,
      "attr_list": [
        "理工类",
        "公办",
        "中科院直属"
      ],
      "hightitle": "中国科学技术大学"
    },
    {
      "school_id": 42,
      "name": "武汉大学",
      "province": "湖北",
      "city": "武汉市",
      "county": "武昌区",
      "type": "综合类",
      "level": "本科",
      "belong": "教育部",
      "rank": "8",
      "dual_class": "双一流",
      "f985": 1,
      "f211": 1,
      "is_dual_class": "38000",
      "nature": "公办",
      "view_total": "3946.8w",
      "content": "江城多山，珞珈独秀；山上有黉，武汉大学。武汉大学是教育部直属重点综合性大学，是国家“985工程”和“211工程”重点建设高校，是首批“双一流”建设高校。武汉大学溯源于1893年清末湖广总督张之洞奏请清政府创办的自强学堂，历经传承演变，1928年定名为国立武汉大学，是近代中国第一批国立大学。1946年，学校已形成文、法、理、工、农、医6大学院并驾齐驱的办学格",
      "email": "wdzsb@whu.edu.cn",
      "school_email": "",
      "site": "https://aoff.whu.edu.cn/",
      "school_site": "https://www.whu.edu.cn/",
      "address": "珞珈山主校区：湖北省武汉市武昌区八一路299号,医学部校区：湖北省武汉市武昌区东湖路115号",
      "phone": "027-68754231",
      "school_phone": "",
      "postcode": "430072",
      "logo": null,
      "create_date": "1893",
      "old_name": "",
      "area": 5195,
      "num_doctor": "53",
      "num_master": "58",
      "num_subject": "5",
      "num_academician": "21",
      "num_library": "731.00万",
      "recommend_master_rate": "33.13",
      "motto": "自强、弘毅、求是、拓新",
      "ruanke_rank": "8",
      "xyh_rank": "9",
      "wsl_rank": "0",
      "qs_rank": "9",
      "us_rank": "90",
      "label_list": [
        "985",
        "211",
        "双一流",
        "强基",
        "101计划",
        "五院四系",
        "中坚九校",
        "电气二龙"
      ],
      "recommend_master_level": "4",
      "is_top": 2,
      "attr_list": [
        "综合类",
        "公办",
        "教育部直属"
      ],
      "hightitle": "武汉大学"
    },
    {
      "school_id": 127,
      "name": "华中科技大学",
      "province": "湖北",
      "city": "武汉市",
      "county": "洪山区",
      "type": "综合类",
      "level": "本科",
      "belong": "教育部",
      "rank": "9",
      "dual_class": "双一流",
      "f985": 1,
      "f211": 1,
      "is_dual_class": "38000",
      "nature": "公办",
      "view_total": "2984.8w",
      "content": "华中科技大学是国家教育部直属重点综合性大学，由原华中理工大学、同济医科大学、武汉城市建设学院于2000年5月26日合并成立，是国家“211工程”重点建设和“985工程”建设高校之一，是首批“双一流”建设高校。学校校园占地7000余亩，园内树木葱茏，碧草如茵，环境优雅，景色秀丽，绿化覆盖率72%，被誉为“森林式大学”。学校教学科研支撑体系完备，各项公共服务设施",
      "email": "zs@hust.edu.cn",
      "school_email": "",
      "site": "https://zsb.hust.edu.cn/",
      "school_site": "https://www.hust.edu.cn/",
      "address": "主校区：湖北省武汉市洪山区珞喻路1037号,同济医学院校区：湖北省武汉市汉硚口区航空路13号",
      "phone": "027-87542228,027-87559946",
      "school_phone": "",
      "postcode": "430074",
      "logo": null,
      "create_date": "2000",
      "old_name": "",
      "area": 7000,
      "num_doctor": "46",
      "num_master": "47",
      "num_subject": "7",
      "num_academician": "20",
      "num_library": "579.00万",
      "recommend_master_rate": "35.73",
      "motto": "明德厚学、求是创新",
      "ruanke_rank": "9",
      "xyh_rank": "10",
      "wsl_rank": "0",
      "qs_rank": "17",
      "us_rank": "91",
      "label_list": [
        "985",
        "211",
        "双一流",
        "强基",
        "101计划",
        "中坚九校",
        "机械五虎",
        "电气四虎",
        "建筑新八校"
      ],
      "recommend_master_level": "4.5",
      "is_top": 2,
      "attr_list": [
        "综合类",
        "公办",
        "教育部直属"
      ],
      "hightitle": "华中科技大学"
    },
    {
      "school_id": 330,
      "name": "西安交通大学",
      "province": "陕西",
      "city": "西安市",
      "county": "碑林区",
      "type": "综合类",
      "level": "本科",
      "belong": "教育部",
      "rank": "10",
      "dual_class": "双一流",
      "f985": 1,
      "f211": 1,
      "is_dual_class": "38000",
      "nature": "公办",
      "view_total": "2377.5w",
      "content": "西安交通大学是我国最早兴办、享誉海内外的著名高等学府，是教育部直属重点大学。西迁以来，一代代交大人扎根西部、服务国家，为西部发展和国家建设作出了卓越贡献，以实际行动铸就了第一批纳入中国共产党人精神谱系的西迁精神。2017年12月，习近平总书记对学校15位老教授来信作出重要指示。在2018年新年贺词中，习近平总书记再次提到“西安交大西迁的老教授”。20",
      "email": "xjtuzs@xjtu.edu.cn",
      "school_email": "",
      "site": "https://zs.xjtu.edu.cn/",
      "school_site": "https://www.xjtu.edu.cn/",
      "address": "兴庆校区：陕西省西安市碑林区咸宁西路28号,雁塔校区：陕西省西安市雁塔区雁塔西路76号,曲江校区：陕西省西安市雁塔区雁翔路99号,中国西部科技创新港校区：陕西省西安市西咸新区沣西新城中国西部科技创新港",
      "phone": "029-82668320",
      "school_phone": "",
      "postcode": "710049",
      "logo": null,
      "create_date": "1896",
      "old_name": "",
      "area": 5000,
      "num_doctor": "40",
      "num_master": "43",
      "num_subject": "8",
      "num_academician": "37",
      "num_library": "603.50万",
      "recommend_master_rate": "37.50",
      "motto": "精勤求学、敦笃励志、果毅力行、忠恕任事",
      "ruanke_rank": "10",
      "xyh_rank": "13",
      "wsl_rank": "0",
      "qs_rank": "11",
      "us_rank": "141",
      "label_list": [
        "985",
        "211",
        "双一流",
        "强基",
        "101计划",
        "C9",
        "中坚九校",
        "机械五虎",
        "电气四虎"
      ],
      "recommend_master_level": "4.5",
      "is_top": 2,
      "attr_list": [
        "综合类",
        "公办",
        "教育部直属"
      ],
      "hightitle": "西安交通大学"
    },
    {
      "school_id": 47,
      "name": "北京航空航天大学",
      "province": "北京",
      "city": "北京市",
      "county": "海淀区",
      "type": "理工类",
      "level": "本科",
      "belong": "工业和信息化部",
      "rank": "11",
      "dual_class": "双一流",
      "f985": 1,
      "f211": 1,
      "is_dual_class": "38000",
      "nature": "公办",
      "view_total": "1294.7w",
      "content": "柏彦故地，巍巍学府。春秋代序，峥嵘航路。1950年，朝鲜战争爆发。抗美援朝战场上，敌我空军力量悬殊。战争的迫切需求推动了新中国航空工业从修理向制造过渡，国家“急需办一所航空大学”。1951年，国家决定将北洋大学、厦门大学、西北工学院航空系并入清华大学航空工程学系，成立清华大学航空工程学院；将云南大学航空工程系并入四川大学航空系；将西南工业专科",
      "email": "zsbgs@buaa.edu.cn",
      "school_email": "",
      "site": "https://zs.buaa.edu.cn/index.htm",
      "school_site": "https://www.buaa.edu.cn/",
      "address": "学院路校区：北京市海淀区学院路37号,沙河校区：北京市昌平区高教园南三街9号",
      "phone": "010-83429695",
      "school_phone": "",
      "postcode": "100083",
      "logo": null,
      "create_date": "1952",
      "old_name": "",
      "area": 4000,
      "num_doctor": "34",
      "num_master": "36",
      "num_subject": "8",
      "num_academician": "22",
      "num_library": "253.00万",
      "recommend_master_rate": "51.80",
      "motto": "",
      "ruanke_rank": "11",
      "xyh_rank": "18",
      "wsl_rank": "0",
      "qs_rank": "20",
      "us_rank": "207",
      "label_list": [
        "985",
        "211",
        "双一流",
        "强基",
        "101计划",
        "国防七子"
      ],
      "recommend_master_level": "5",
      "is_top": 2,
      "attr_list": [
        "理工类",
        "公办",
        "工信部直属"
      ],
      "hightitle": "北京航空航天大学"
    },
    {
      "school_id": 104,
      "name": "中山大学",
      "province": "广东",
      "city": "广州市",
      "county": "",
      "type": "综合类",
      "level": "本科",
      "belong": "教育部",
      "rank": "12",
      "dual_class": "双一流",
      "f985": 1,
      "f211": 1,
      "is_dual_class": "38000",
      "nature": "公办",
      "view_total": "3787.4w",
      "content": "中山大学是伟大的民族英雄、伟大的爱国主义者、中国民主革命的伟大先驱孙中山先生于1924年亲手创办，中国共产党早期领导人共同创建的大学，是中国传播马克思主义的重要发源地之一，具有优良革命传统、爱国奋斗精神和卓越品格追求。中山大学起初校名为国立广东大学。孙中山先生逝世后，学校于1926年定名为国立中山大学。今日的中山大学，由1952年院系调整后分设的",
      "email": "adado@mail.sysu.edu.cn",
      "school_email": "",
      "site": "https://admission.sysu.edu.cn",
      "school_site": "https://www.sysu.edu.cn/",
      "address": "广州校区南校园：广东省广州市海珠区新港西路135号,广州校区北校园：广东省广州市越秀区中山二路74号,广州校区东校园：广州市番禺区大学城外环东路132号,珠海校区：广东省珠海市香洲区唐家湾,深圳校区：广东省深圳市光明区公常路66号",
      "phone": "020-84110558",
      "school_phone": "",
      "postcode": "510275",
      "logo": null,
      "create_date": "1924",
      "old_name": "",
      "area": 13725,
      "num_doctor": "62",
      "num_master": "69",
      "num_subject": "2",
      "num_academician": "20",
      "num_library": "1000.00万",
      "recommend_master_rate": "28.24",
      "motto": "博学 审问 慎思 明辨 笃行",
      "ruanke_rank": "12",
      "xyh_rank": "14",
      "wsl_rank": "0",
      "qs_rank": "8",
      "us_rank": "85",
      "label_list": [
        "985",
        "211",
        "双一流",
        "强基",
        "101计划",
        "中坚九校"
      ],
      "recommend_master_level": "3.5",
      "is_top": 2,
      "attr_list": [
        "综合类",
        "公办",
        "教育部直属"
      ],
      "hightitle": "中山大学"
    },
    {
      "school_id": 143,
      "name": "北京理工大学",
      "province": "北京",
      "city": "北京市",
      "county": "海淀区",
      "type": "理工类",
      "level": "本科",
      "belong": "工业和信息化部",
      "rank": "13",
      "dual_class": "双一流",
      "f985": 1,
      "f211": 1,
      "is_dual_class": "38000",
      "nature": "公办",
      "view_total": "1930.4w",
      "content": "北京理工大学的前身是1940年诞生于延安的自然科学院，是中国共产党历史上第一个开展自然科学教学与研究的专门机构。毛泽东同志亲自题写校名，无产阶级革命家李富春，无产阶级革命家、教育家徐特立，无产阶级革命家、无线电专家、经济专家李强等先后担任学校主要领导。1949年，学校迁入北京；1952年，定名为北京工业学院，成为新中国第一所国防工业院校；1988年，更",
      "email": "admission@bit.edu.cn",
      "school_email": "",
      "site": "https://admission.bit.edu.cn",
      "school_site": "https://www.bit.edu.cn/",
      "address": "中关村校区：北京市海淀区中关村南大街5号,良乡校区：北京市房山区良乡东路与学园北街交叉口,西山校区：北京市海淀区冷泉东路16号,怀来校区：河北省张家口市怀来县,珠海校区：广东省珠海市唐家湾金凤路6号",
      "phone": "010-68913345,010-68949926,010-68911460,010-68911461",
      "school_phone": "",
      "postcode": "100081",
      "logo": null,
      "create_date": "1940",
      "old_name": "北京工业学院",
      "area": 9150,
      "num_doctor": "35",
      "num_master": "35",
      "num_subject": "4",
      "num_academician": "7",
      "num_library": "429.00万",
      "recommend_master_rate": "32.00",
      "motto": "德以明理、学以精工",
      "ruanke_rank": "13",
      "xyh_rank": "21",
      "wsl_rank": "0",
      "qs_rank": "19",
      "us_rank": "156",
      "label_list": [
        "985",
        "211",
        "双一流",
        "强基",
        "101计划",
        "E9",
        "国防七子",
        "中坚九校",
        "兵工七子"
      ],
      "recommend_master_level": "4",
      "is_top": 2,
      "attr_list": [
        "理工类",
        "公办",
        "工信部直属"
      ],
      "hightitle": "北京理工大学"
    },
    {
      "school_id": 573,
      "name": "北京协和医学院",
      "province": "北京",
      "city": "北京市",
      "county": "东城区",
      "type": "医药类",
      "level": "本科",
      "belong": "国家卫生健康委员会",
      "rank": "14",
      "dual_class": "双一流",
      "f985": 2,
      "f211": 2,
      "is_dual_class": "38000",
      "nature": "公办",
      "view_total": "325.2w",
      "content": "中国医学科学院成立于1956年，北京协和医学院成立于1917年，中国医学科学院北京协和医学院自1957年起实行院校合一的管理体制，是我国最高医学研究机构和领衔医学教育机构。院校始终牢记初心使命，以引领我国医学科技教育发展和维护人民健康为己任，教育人才辈出，科研硕果累累，医疗领衔行业，为我国现代科学医学体系的建立和发展做出了重要贡献。建立之初，北京",
      "email": "gkzs@pumc.edu.cn",
      "school_email": "",
      "site": "https://gkxc.pumc.edu.cn/pumc/#/index",
      "school_site": "https://www.pumc.edu.cn",
      "address": "北京市东城区东单三条9号",
      "phone": "010-65105809,010-88771239",
      "school_phone": "",
      "postcode": "100730",
      "logo": null,
      "create_date": "1917",
      "old_name": "清华大学医学部",
      "area": 0,
      "num_doctor": "9",
      "num_master": "0",
      "num_subject": "0",
      "num_academician": "24",
      "num_library": "0.00万",
      "recommend_master_rate": "36.30",
      "motto": "",
      "ruanke_rank": "13",
      "xyh_rank": "33",
      "wsl_rank": "0",
      "qs_rank": "0",
      "us_rank": "468",
      "label_list": [
        "双一流"
      ],
      "recommend_master_level": "4.5",
      "is_top": 2,
      "attr_list": [
        "本科",
        "医药类",
        "公办",
        "国家卫健委直属"
      ],
      "hightitle": "北京协和医学院"
    },
    {
      "school_id": 34,
      "name": "哈尔滨工业大学",
      "province": "黑龙江",
      "city": "哈尔滨市",
      "county": "南岗区",
      "type": "理工类",
      "level": "本科",
      "belong": "工业和信息化部",
      "rank": "15",
      "dual_class": "双一流",
      "f985": 1,
      "f211": 1,
      "is_dual_class": "38000",
      "nature": "公办",
      "view_total": "2311.8w",
      "content": "2020年6月7日，习近平总书记致信祝贺哈尔滨工业大学建校100周年。贺信指出，哈尔滨工业大学历史悠久。新中国成立以来，在党的领导下，学校扎根东北、爱国奉献、艰苦创业，打造了一大批国之重器，培养了一大批杰出人才，为党和人民作出了重要贡献。希望哈尔滨工业大学在新的起点上，坚持社会主义办学方向，紧扣立德树人根本任务，在教书育人、科研攻关等工作中，",
      "email": "",
      "school_email": "",
      "site": "https://zsb.hit.edu.cn/",
      "school_site": "https://www.hit.edu.cn",
      "address": "哈尔滨校区：黑龙江省哈尔滨市南岗区西大直街92号,威海校区：山东省威海市环翠区文化西路2号,深圳校区：广东省深圳市南山区西丽深圳大学城哈工大校区",
      "phone": "0451-53985216",
      "school_phone": "",
      "postcode": "150001",
      "logo": null,
      "create_date": "1920",
      "old_name": "",
      "area": 0,
      "num_doctor": "32",
      "num_master": "42",
      "num_subject": "9",
      "num_academician": "23",
      "num_library": "357.00万",
      "recommend_master_rate": "35.60",
      "motto": "规格严格，功夫到家",
      "ruanke_rank": "14",
      "xyh_rank": "12",
      "wsl_rank": "0",
      "qs_rank": "10",
      "us_rank": "128",
      "label_list": [
        "985",
        "211",
        "双一流",
        "强基",
        "101计划",
        "C9",
        "E9",
        "国防七子",
        "中坚九校",
        "机械五虎",
        "建筑老八校"
      ],
      "recommend_master_level": "4.5",
      "is_top": 2,
      "attr_list": [
        "理工类",
        "公办",
        "工信部直属"
      ],
      "hightitle": "哈尔滨工业大学"
    },
    {
      "school_id": 99,
      "name": "四川大学",
      "province": "四川",
      "city": "成都市",
      "county": "武侯区",
      "type": "综合类",
      "level": "本科",
      "belong": "教育部",
      "rank": "16",
      "dual_class": "双一流",
      "f985": 1,
      "f211": 1,
      "is_dual_class": "38000",
      "nature": "公办",
      "view_total": "4786.3w",
      "content": "岷峨挺秀，锦水含章。巍巍学府，德渥群芳。四川大学是教育部直属全国重点大学，是国家布局在中国西部的重点建设的高水平研究型综合大学，是国家“双一流”建设高校（A类）。四川大学地处中国历史文化名城——“天府之国”的成都，有望江、华西和江安三个校区，占地面积7050亩，校舍建筑面积281.7万平方米。学校正与眉山市合作共建四川大学眉山校区。校园环境幽雅",
      "email": "zs@scu.edu.cn",
      "school_email": "",
      "site": "https://zs.scu.edu.cn",
      "school_site": "https://www.scu.edu.cn/",
      "address": "望江校区：四川省成都市武侯区一环路南一段24号,华西校区：四川省成都市武侯区人民南路三段17号,江安校区：四川省成都市双流区川大路二段2号",
      "phone": "028-86081605,028-86080605",
      "school_phone": "",
      "postcode": "610065",
      "logo": null,
      "create_date": "1896",
      "old_name": "",
      "area": 7050,
      "num_doctor": "53",
      "num_master": "2",
      "num_subject": "0",
      "num_academician": "11",
      "num_library": "700.00万",
      "recommend_master_rate": "26.31",
      "motto": "海纳百川，有容乃大",
      "ruanke_rank": "15",
      "xyh_rank": "16",
      "wsl_rank": "0",
      "qs_rank": "24",
      "us_rank": "182",
      "label_list": [
        "985",
        "211",
        "双一流",
        "强基",
        "101计划"
      ],
      "recommend_master_level": "3.5",
      "is_top": 2,
      "attr_list": [
        "综合类",
        "公办",
        "教育部直属"
      ],
      "hightitle": "四川大学"
    },
    {
      "school_id": 109,
      "name": "东南大学",
      "province": "江苏",
      "city": "南京市",
      "county": "玄武区",
      "type": "综合类",
      "level": "本科",
      "belong": "教育部",
      "rank": "17",
      "dual_class": "双一流",
      "f985": 1,
      "f211": 1,
      "is_dual_class": "38000",
      "nature": "公办",
      "view_total": "2426.3w",
      "content": "东南大学坐落于六朝古都南京，是享誉海内外的著名高等学府。学校是国家教育部直属并与江苏省共建的全国重点大学，是国家“985工程”和“211工程”重点建设大学之一。2017年，东南大学入选世界一流大学建设A类高校名单。东南大学是一所历史悠久、底蕴深厚的大学。学校创建于1902年的三江师范学堂，后历经两江师范学堂、南京高等师范学校、国立东南大学、国立中央大",
      "email": "zhaoban@seu.edu.cn",
      "school_email": "",
      "site": "https://zsb.seu.edu.cn/",
      "school_site": "https://www.seu.edu.cn/",
      "address": "四牌楼校区：江苏省南京市玄武区新街口街道大石桥社区四牌楼2号,九龙湖校区：江苏省南京市江宁区东南大学路2号,丁家桥校区：江苏省南京市鼓楼区丁家桥87号,无锡校区：江苏省无锡市新吴区菱湖大道99号,苏州校区：江苏省苏州市苏州工业园区林泉街399号",
      "phone": "025-52090271",
      "school_phone": "",
      "postcode": "211189",
      "logo": null,
      "create_date": "1902",
      "old_name": "",
      "area": 5888,
      "num_doctor": "44",
      "num_master": "53",
      "num_subject": "0",
      "num_academician": "12",
      "num_library": "417.00万",
      "recommend_master_rate": "34.99",
      "motto": "止于至善",
      "ruanke_rank": "16",
      "xyh_rank": "20",
      "wsl_rank": "0",
      "qs_rank": "26",
      "us_rank": "155",
      "label_list": [
        "985",
        "211",
        "双一流",
        "强基",
        "101计划",
        "E9",
        "中坚九校",
        "建筑老八校"
      ],
      "recommend_master_level": "4",
      "is_top": 2,
      "attr_list": [
        "综合类",
        "公办",
        "教育部直属"
      ],
      "hightitle": "东南大学"
    },
    {
      "school_id": 46,
      "name": "中国人民大学",
      "province": "北京",
      "city": "北京市",
      "county": "海淀区",
      "type": "综合类",
      "level": "本科",
      "belong": "教育部",
      "rank": "18",
      "dual_class": "双一流",
      "f985": 1,
      "f211": 1,
      "is_dual_class": "38000",
      "nature": "公办",
      "view_total": "1575.2w",
      "content": "中国人民大学（RenminUniversityofChina）是中国共产党创办的第一所新型正规大学，直属于教育部，由教育部与北京市共建。现任党委书记为张东刚、校长为林尚立。历史沿革和领导关怀中国人民大学前身是1937年诞生于抗日战争烽火中的陕北公学，以及后来的华北联合大学和北方大学、华北大学。学校始终与党和国家同呼吸、共命运，始终得到党中央的亲切关怀和高度重视。陕北",
      "email": "zsb@ruc.edu.cn",
      "school_email": "",
      "site": "https://rdzs.ruc.edu.cn/cms/",
      "school_site": "https://www.ruc.edu.cn",
      "address": "校本部：北京市海淀区中关村大街59号,苏州校区：江苏省苏州市苏州工业园区仁爱路158号,深圳研究院校区：广东省深圳市南山区科技南三道深投控创智天地大厦南侧",
      "phone": "400-012-3517",
      "school_phone": "",
      "postcode": "100872",
      "logo": null,
      "create_date": "1937",
      "old_name": "",
      "area": 1044,
      "num_doctor": "27",
      "num_master": "37",
      "num_subject": "8",
      "num_academician": "0",
      "num_library": "439.00万",
      "recommend_master_rate": "40.29",
      "motto": "实事求是",
      "ruanke_rank": "17",
      "xyh_rank": "12",
      "wsl_rank": "0",
      "qs_rank": "14",
      "us_rank": "394",
      "label_list": [
        "985",
        "211",
        "双一流",
        "强基",
        "101计划",
        "五院四系"
      ],
      "recommend_master_level": "5",
      "is_top": 2,
      "attr_list": [
        "综合类",
        "公办",
        "教育部直属"
      ],
      "hightitle": "中国人民大学"
    },
    {
      "school_id": 73,
      "name": "同济大学",
      "province": "上海",
      "city": "上海市",
      "county": "杨浦区",
      "type": "综合类",
      "level": "本科",
      "belong": "教育部",
      "rank": "19",
      "dual_class": "双一流",
      "f985": 1,
      "f211": 1,
      "is_dual_class": "38000",
      "nature": "公办",
      "view_total": "2409.1w",
      "content": "同济的100年，是与中华民族命运休戚与共的100年；同济的100年，是与祖国科教事业心手相牵的100年；同济的100年，是与上海城市发展相濡以沫的100年。——摘自习近平同志在同济大学建校100周年庆祝大会上的讲话同心同德同舟楫，济人济事济天下！同济大学历史悠久、声誉卓著，是中国最早的国立大学之一，是教育部直属并与上海市共建的全国重点大学。经过118年的发展，同",
      "email": "tjzsb@tongji.edu.cn",
      "school_email": "newscenter@tongji.edu.cn",
      "site": "https://bkzs.tongji.edu.cn/",
      "school_site": "https://www.tongji.edu.cn",
      "address": "四平路校区：上海市杨浦区四平路1239号,嘉定校区：上海市嘉定区曹安公路4800号,沪西校区：上海市普陀区真南路500号,沪北校区：上海市静安区中山北路727号",
      "phone": "021-65982643",
      "school_phone": "",
      "postcode": "200092",
      "logo": null,
      "create_date": "1907",
      "old_name": "",
      "area": 4140,
      "num_doctor": "37",
      "num_master": "45",
      "num_subject": "3",
      "num_academician": "0",
      "num_library": "473.00万",
      "recommend_master_rate": "37.72",
      "motto": "同舟共济",
      "ruanke_rank": "18",
      "xyh_rank": "17",
      "wsl_rank": "0",
      "qs_rank": "12",
      "us_rank": "124",
      "label_list": [
        "985",
        "211",
        "双一流",
        "强基",
        "101计划",
        "E9",
        "建筑老八校"
      ],
      "recommend_master_level": "4.5",
      "is_top": 2,
      "attr_list": [
        "综合类",
        "公办",
        "教育部直属"
      ],
      "hightitle": "同济大学"
    },
    {
      "school_id": 52,
      "name": "北京师范大学",
      "province": "北京",
      "city": "北京市",
      "county": "海淀区",
      "type": "综合类",
      "level": "本科",
      "belong": "教育部",
      "rank": "20",
      "dual_class": "双一流",
      "f985": 1,
      "f211": 1,
      "is_dual_class": "38000",
      "nature": "公办",
      "view_total": "1457.8w",
      "content": "北京师范大学是教育部直属重点大学，是一所以教师教育、教育科学和文理基础学科为主要特色的著名学府。学校的前身是1902年创立的京师大学堂师范馆，1908年改称京师优级师范学堂，独立设校，1912年改名为北京高等师范学校。1923年学校更名为北京师范大学，成为中国历史上第一所师范大学。1931年、1952年北平女子师范大学、辅仁大学先后并入北京师范大学。百余年来，北",
      "email": "zsb@bnu.edu.cn",
      "school_email": "",
      "site": "https://admission.bnu.edu.cn/",
      "school_site": "https://www.bnu.edu.cn",
      "address": "北京校区：北京市海淀区新街口外大街19号,珠海校区：广东省珠海市香洲区唐家湾镇宁堂社区金凤路18号",
      "phone": "010-58807962",
      "school_phone": "",
      "postcode": "100875",
      "logo": null,
      "create_date": "1902",
      "old_name": "",
      "area": 0,
      "num_doctor": "34",
      "num_master": "36",
      "num_subject": "0",
      "num_academician": "7",
      "num_library": "584.00万",
      "recommend_master_rate": "39.44",
      "motto": "学为人师 行为世范",
      "ruanke_rank": "19",
      "xyh_rank": "14",
      "wsl_rank": "0",
      "qs_rank": "13",
      "us_rank": "173",
      "label_list": [
        "985",
        "211",
        "双一流",
        "强基",
        "101计划",
        "师大六姐妹"
      ],
      "recommend_master_level": "4.5",
      "is_top": 2,
      "attr_list": [
        "综合类",
        "公办",
        "教育部直属"
      ],
      "hightitle": "北京师范大学"
    }
  ]
}